porcatroia/__init__.py
porcatroia/porcatroia.py
porcatroia-1.0.1.dist-info/METADATA
porcatroia-1.0.1.dist-info/WHEEL
porcatroia-1.0.1.dist-info/top_level.txt
porcatroia-1.0.1.dist-info/RECORD
