Metadata-Version: 2.4
Name: porcatroia
Version: 1.0.1
Summary: Se ti si fanculizza il codice, questo programma sclera per te
Author: AdrianoTech
License: Creative Commons 3.0
Requires-Python: >=3.7
Requires-Dist: colorama
